StreamDeck/DeviceManager.py
StreamDeck/ProductIDs.py
StreamDeck/__init__.py
StreamDeck/Devices/StreamDeck.py
StreamDeck/Devices/StreamDeckMini.py
StreamDeck/Devices/StreamDeckNeo.py
StreamDeck/Devices/StreamDeckOriginal.py
StreamDeck/Devices/StreamDeckOriginalV2.py
StreamDeck/Devices/StreamDeckPedal.py
StreamDeck/Devices/StreamDeckPlus.py
StreamDeck/Devices/StreamDeckXL.py
StreamDeck/Devices/__init__.py
StreamDeck/ImageHelpers/PILHelper.py
StreamDeck/ImageHelpers/__init__.py
StreamDeck/Transport/Dummy.py
StreamDeck/Transport/LibUSBHIDAPI.py
StreamDeck/Transport/Transport.py
StreamDeck/Transport/__init__.py
streamdeck-0.9.7.dist-info/licenses/LICENSE
streamdeck-0.9.7.dist-info/METADATA
streamdeck-0.9.7.dist-info/WHEEL
streamdeck-0.9.7.dist-info/top_level.txt
streamdeck-0.9.7.dist-info/RECORD
