Metadata-Version: 2.4
Name: streamdeck
Version: 0.9.7
Summary: Library to control Elgato StreamDeck devices.
Home-page: https://github.com/abcminiuser/python-elgato-streamdeck
Author: Dean Camera
Author-email: dean@fourwalledcubicle.com
License: MIT
Requires-Python: >=3.9
License-File: LICENSE
Dynamic: author
Dynamic: author-email
Dynamic: description
Dynamic: description-content-type
Dynamic: home-page
Dynamic: license
Dynamic: license-file
Dynamic: requires-python
Dynamic: summary
